{
  "data": {
    "id": 18475817,
    "sport_id": 1,
    "league_id": 711,
    "season_id": 16497,
    "stage_id": 77445494,
    "group_id": null,
    "aggregate_id": 28590,
    "round_id": null,
    "state_id": 5,
    "venue_id": 2562,
    "name": "Tunisia vs Mali",
    "starting_at": "2022-03-29 19:30:00",
    "result_info": "Game ended in draw.",
    "leg": "2/2",
    "details": null,
    "length": 90,
    "placeholder": false,
    "has_odds": true,
    "has_premium_odds": false,
    "starting_at_timestamp": 1648582200,
    "predictions": [
      {
        "id": 3474291,
        "fixture_id": 18475817,
        "predictions": {
          "bet": "X",
          "bookmaker": "williamhill",
          "odd": 3,
          "is_value": false,
          "stake": 0.62,
          "fair_odd": 2.84
        },
        "type_id": 33
      },
      {
        "id": 3727474,
        "fixture_id": 18475817,
        "predictions": {
          "home": 41.876,
          "away": 33.585,
          "draw": 24.534
        },
        "type_id": 237
      },
      {
        "id": 3727475,
        "fixture_id": 18475817,
        "predictions": {
          "scores": {
            "0-0": 5.366,
            "0-1": 7.347,
            "0-2": 5.03,
            "0-3": 2.295,
            "0-4": 0.786,
            "0-5": 0.215,
            "0-6": 0.049,
            "0-7": 0.01,
            "0-8": 0.002,
            "1-0": 8.349,
            "1-1": 11.43,
            "1-2": 7.826,
            "1-3": 3.572,
            "1-4": 1.223,
            "1-5": 0.335,
            "1-6": 0.076,
            "1-7": 0.015,
            "1-8": 0.003,
            "2-0": 6.495,
            "2-1": 8.893,
            "2-2": 6.088,
            "2-3": 2.779,
            "2-4": 0.951,
            "2-5": 0.26,
            "2-6": 0.059,
            "2-7": 0.012,
            "2-8": 0.002,
            "3-0": 3.369,
            "3-1": 4.612,
            "3-2": 3.157,
            "3-3": 1.441,
            "3-4": 0.493,
            "3-5": 0.135,
            "3-6": 0.031,
            "3-7": 0.006,
            "3-8": 0.001,
            "4-0": 1.31,
            "4-1": 1.794,
            "4-2": 1.228,
            "4-3": 0.561,
            "4-4": 0.192,
            "4-5": 0.053,
            "4-6": 0.012,
            "4-7": 0.002,
            "5-0": 0.408,
            "5-1": 0.558,
            "5-2": 0.382,
            "5-3": 0.174,
            "5-4": 0.06,
            "5-5": 0.016,
            "5-6": 0.004,
            "5-7": 0.001,
            "6-0": 0.106,
            "6-1": 0.145,
            "6-2": 0.099,
            "6-3": 0.045,
            "6-4": 0.015,
            "6-5": 0.004,
            "6-6": 0.001,
            "7-0": 0.024,
            "7-1": 0.032,
            "7-2": 0.022,
            "7-3": 0.01,
            "7-4": 0.003,
            "7-5": 0.001,
            "8-0": 0.005,
            "8-1": 0.006,
            "8-2": 0.004,
            "8-3": 0.002,
            "8-4": 0.001,
            "9-0": 0.001,
            "9-1": 0.001,
            "9-2": 0.001
          }
        },
        "type_id": 240
      },
      {
        "id": 3727476,
        "fixture_id": 18475817,
        "predictions": {
          "yes": 58.83,
          "no": 41.17
        },
        "type_id": 231
      }
    ],
    "odds": [
      {
        "id": 484269853,
        "fixture_id": 18475817,
        "market_id": 44,
        "bookmaker_id": 55,
        "label": "Odd",
        "value": "1.95",
        "name": "Odd",
        "sort_order": null,
        "market_description": "Odd/Even",
        "probability": "51.28%",
        "dp3": "1.950",
        "fractional": "39/20",
        "american": "-106",
        "winning": false,
        "stopped": false,
        "total": null,
        "handicap": null,
        "participants": null,
        "created_at": "2022-03-26T19:16:25.000000Z",
        "original_label": null,
        "latest_bookmaker_update": "2022-03-29 19:18:07"
      },
      {
        "id": 484267781,
        "fixture_id": 18475817,
        "market_id": 1,
        "bookmaker_id": 35,
        "label": "1",
        "value": "2.46",
        "name": "1",
        "sort_order": null,
        "market_description": "Fulltime Result",
        "probability": "40.65%",
        "dp3": "2.460",
        "fractional": "32/13",
        "american": "146",
        "winning": false,
        "stopped": false,
        "total": null,
        "handicap": null,
        "participants": "18554",
        "created_at": "2022-03-24T06:05:19.000000Z",
        "original_label": null,
        "latest_bookmaker_update": "2022-03-29 19:28:28"
      },
      {
        "id": 484267790,
        "fixture_id": 18475817,
        "market_id": 1,
        "bookmaker_id": 35,
        "label": "X",
        "value": "3.01",
        "name": "X",
        "sort_order": null,
        "market_description": "Fulltime Result",
        "probability": "33.22%",
        "dp3": "3.010",
        "fractional": "232/77",
        "american": "200",
        "winning": true,
        "stopped": false,
        "total": null,
        "handicap": null,
        "participants": null,
        "created_at": "2022-03-24T06:05:19.000000Z",
        "original_label": null,
        "latest_bookmaker_update": "2022-03-29 19:28:28"
      },
      {
        "id": 484267794,
        "fixture_id": 18475817,
        "market_id": 1,
        "bookmaker_id": 35,
        "label": "2",
        "value": "3.42",
        "name": "2",
        "sort_order": null,
        "market_description": "Fulltime Result",
        "probability": "29.24%",
        "dp3": "3.420",
        "fractional": "41/12",
        "american": "242",
        "winning": false,
        "stopped": false,
        "total": null,
        "handicap": null,
        "participants": "18731",
        "created_at": "2022-03-24T06:05:19.000000Z",
        "original_label": null,
        "latest_bookmaker_update": "2022-03-29 19:28:28"
      },
      {
        "id": 484267797,
        "fixture_id": 18475817,
        "market_id": 80,
        "bookmaker_id": 35,
        "label": "Under",
        "value": "4.50",
        "name": "0.5",
        "sort_order": null,
        "market_description": "Goals Over/Under",
        "probability": "22.22%",
        "dp3": "4.500",
        "fractional": "9/2",
        "american": "350",
        "winning": true,
        "stopped": false,
        "total": "0.5",
        "handicap": null,
        "participants": null,
        "created_at": "2022-03-24T06:05:19.000000Z",
        "original_label": null,
        "latest_bookmaker_update": "2022-03-29 19:28:28"
      },
      {
        "id": 484267800,
        "fixture_id": 18475817,
        "market_id": 80,
        "bookmaker_id": 35,
        "label": "Over",
        "value": "1.22",
        "name": "0.5",
        "sort_order": null,
        "market_description": "Goals Over/Under",
        "probability": "81.97%",
        "dp3": "1.220",
        "fractional": "50/41",
        "american": "-455",
        "winning": false,
        "stopped": false,
        "total": "0.5",
        "handicap": null,
        "participants": null,
        "created_at": "2022-03-24T06:05:19.000000Z",
        "original_label": null,
        "latest_bookmaker_update": "2022-03-29 19:28:28"
      },
      {
        "id": 484267803,
        "fixture_id": 18475817,
        "market_id": 80,
        "bookmaker_id": 35,
        "label": "Over",
        "value": "1.25",
        "name": "0.75",
        "sort_order": null,
        "market_description": "Goals Over/Under",
        "probability": "80%",
        "dp3": "1.250",
        "fractional": "5/4",
        "american": "-400",
        "winning": false,
        "stopped": false,
        "total": "0.75",
        "handicap": null,
        "participants": null,
        "created_at": "2022-03-24T06:05:19.000000Z",
        "original_label": null,
        "latest_bookmaker_update": "2022-03-29 19:28:28"
      },
      {
        "id": 484267805,
        "fixture_id": 18475817,
        "market_id": 80,
        "bookmaker_id": 35,
        "label": "Under",
        "value": "4.03",
        "name": "0.75",
        "sort_order": null,
        "market_description": "Goals Over/Under",
        "probability": "24.81%",
        "dp3": "4.030",
        "fractional": "121/30",
        "american": "303",
        "winning": true,
        "stopped": false,
        "total": "0.75",
        "handicap": null,
        "participants": null,
        "created_at": "2022-03-24T06:05:19.000000Z",
        "original_label": null,
        "latest_bookmaker_update": "2022-03-29 19:28:28"
      },
      {
        "id": 484267807,
        "fixture_id": 18475817,
        "market_id": 80,
        "bookmaker_id": 35,
        "label": "Under",
        "value": "3.45",
        "name": "1.0",
        "sort_order": null,
        "market_description": "Goals Over/Under",
        "probability": "28.99%",
        "dp3": "3.450",
        "fractional": "69/20",
        "american": "245",
        "winning": true,
        "stopped": false,
        "total": "1.0",
        "handicap": null,
        "participants": null,
        "created_at": "2022-03-24T06:05:19.000000Z",
        "original_label": null,
        "latest_bookmaker_update": "2022-03-29 19:28:28"
      },
      {
        "id": 484267809,
        "fixture_id": 18475817,
        "market_id": 80,
        "bookmaker_id": 35,
        "label": "Over",
        "value": "1.33",
        "name": "1.0",
        "sort_order": null,
        "market_description": "Goals Over/Under",
        "probability": "75.19%",
        "dp3": "1.330",
        "fractional": "97/73",
        "american": "-304",
        "winning": false,
        "stopped": false,
        "total": "1.0",
        "handicap": null,
        "participants": null,
        "created_at": "2022-03-24T06:05:19.000000Z",
        "original_label": null,
        "latest_bookmaker_update": "2022-03-29 19:28:28"
      },
      {
        "id": 484267948,
        "fixture_id": 18475817,
        "market_id": 6,
        "bookmaker_id": 35,
        "label": "2",
        "value": "1.19",
        "name": "+1",
        "sort_order": null,
        "market_description": "Asian Handicap",
        "probability": "84.03%",
        "dp3": "1.190",
        "fractional": "25/21",
        "american": "-527",
        "winning": false,
        "stopped": false,
        "total": null,
        "handicap": "+1",
        "participants": "18731",
        "created_at": "2022-03-24T07:31:45.000000Z",
        "original_label": null,
        "latest_bookmaker_update": "2022-03-29 19:28:28"
      },
      {
        "id": 484267950,
        "fixture_id": 18475817,
        "market_id": 6,
        "bookmaker_id": 35,
        "label": "1",
        "value": "1.09",
        "name": "+1",
        "sort_order": null,
        "market_description": "Asian Handicap",
        "probability": "91.74%",
        "dp3": "1.090",
        "fractional": "12/11",
        "american": "-1112",
        "winning": false,
        "stopped": false,
        "total": null,
        "handicap": "+1",
        "participants": "18554",
        "created_at": "2022-03-24T07:31:45.000000Z",
        "original_label": null,
        "latest_bookmaker_update": "2022-03-29 19:28:28"
      },
      {
        "id": 484267953,
        "fixture_id": 18475817,
        "market_id": 6,
        "bookmaker_id": 35,
        "label": "2",
        "value": "7.68",
        "name": "-1",
        "sort_order": null,
        "market_description": "Asian Handicap",
        "probability": "13.02%",
        "dp3": "7.680",
        "fractional": "123/16",
        "american": "668",
        "winning": false,
        "stopped": false,
        "total": null,
        "handicap": "-1",
        "participants": "18731",
        "created_at": "2022-03-24T07:31:45.000000Z",
        "original_label": null,
        "latest_bookmaker_update": "2022-03-29 19:28:28"
      },
      {
        "id": 484267956,
        "fixture_id": 18475817,
        "market_id": 6,
        "bookmaker_id": 35,
        "label": "1",
        "value": "5.43",
        "name": "-1.25",
        "sort_order": null,
        "market_description": "Asian Handicap",
        "probability": "18.42%",
        "dp3": "5.430",
        "fractional": "38/7",
        "american": "443",
        "winning": false,
        "stopped": false,
        "total": null,
        "handicap": "-1.25",
        "participants": "18554",
        "created_at": "2022-03-24T07:31:45.000000Z",
        "original_label": null,
        "latest_bookmaker_update": "2022-03-29 19:28:28"
      },
      {
        "id": 484267961,
        "fixture_id": 18475817,
        "market_id": 6,
        "bookmaker_id": 35,
        "label": "2",
        "value": "8.59",
        "name": "-1.25",
        "sort_order": null,
        "market_description": "Asian Handicap",
        "probability": "11.64%",
        "dp3": "8.590",
        "fractional": "103/12",
        "american": "759",
        "winning": false,
        "stopped": false,
        "total": null,
        "handicap": "-1.25",
        "participants": "18731",
        "created_at": "2022-03-24T07:31:45.000000Z",
        "original_label": null,
        "latest_bookmaker_update": "2022-03-29 19:28:28"
      },
      {
        "id": 484267965,
        "fixture_id": 18475817,
        "market_id": 6,
        "bookmaker_id": 35,
        "label": "1",
        "value": "1.07",
        "name": "+1.25",
        "sort_order": null,
        "market_description": "Asian Handicap",
        "probability": "93.46%",
        "dp3": "1.070",
        "fractional": "31/29",
        "american": "-1429",
        "winning": false,
        "stopped": false,
        "total": null,
        "handicap": "+1.25",
        "participants": "18554",
        "created_at": "2022-03-24T07:31:45.000000Z",
        "original_label": null,
        "latest_bookmaker_update": "2022-03-29 19:28:28"
      },
      {
        "id": 484267971,
        "fixture_id": 18475817,
        "market_id": 6,
        "bookmaker_id": 35,
        "label": "2",
        "value": "1.15",
        "name": "+1.25",
        "sort_order": null,
        "market_description": "Asian Handicap",
        "probability": "86.96%",
        "dp3": "1.150",
        "fractional": "23/20",
        "american": "-667",
        "winning": false,
        "stopped": false,
        "total": null,
        "handicap": "+1.25",
        "participants": "18731",
        "created_at": "2022-03-24T07:31:45.000000Z",
        "original_label": null,
        "latest_bookmaker_update": "2022-03-29 19:28:28"
      },
      {
        "id": 484267975,
        "fixture_id": 18475817,
        "market_id": 6,
        "bookmaker_id": 35,
        "label": "2",
        "value": "1.13",
        "name": "+1.5",
        "sort_order": null,
        "market_description": "Asian Handicap",
        "probability": "88.5%",
        "dp3": "1.130",
        "fractional": "26/23",
        "american": "-770",
        "winning": false,
        "stopped": false,
        "total": null,
        "handicap": "+1.5",
        "participants": "18731",
        "created_at": "2022-03-24T07:31:45.000000Z",
        "original_label": null,
        "latest_bookmaker_update": "2022-03-29 19:28:28"
      },
      {
        "id": 484267980,
        "fixture_id": 18475817,
        "market_id": 6,
        "bookmaker_id": 35,
        "label": "1",
        "value": "6.13",
        "name": "-1.5",
        "sort_order": null,
        "market_description": "Asian Handicap",
        "probability": "16.31%",
        "dp3": "6.130",
        "fractional": "49/8",
        "american": "513",
        "winning": false,
        "stopped": false,
        "total": null,
        "handicap": "-1.5",
        "participants": "18554",
        "created_at": "2022-03-24T07:31:45.000000Z",
        "original_label": null,
        "latest_bookmaker_update": "2022-03-29 19:28:28"
      },
      {
        "id": 484267984,
        "fixture_id": 18475817,
        "market_id": 6,
        "bookmaker_id": 35,
        "label": "1",
        "value": "1.06",
        "name": "+1.5",
        "sort_order": null,
        "market_description": "Asian Handicap",
        "probability": "94.34%",
        "dp3": "1.060",
        "fractional": "35/33",
        "american": "-1667",
        "winning": false,
        "stopped": false,
        "total": null,
        "handicap": "+1.5",
        "participants": "18554",
        "created_at": "2022-03-24T07:31:45.000000Z",
        "original_label": null,
        "latest_bookmaker_update": "2022-03-29 19:28:28"
      },
      {
        "id": 484267989,
        "fixture_id": 18475817,
        "market_id": 6,
        "bookmaker_id": 35,
        "label": "2",
        "value": "9.50",
        "name": "-1.5",
        "sort_order": null,
        "market_description": "Asian Handicap",
        "probability": "10.53%",
        "dp3": "9.500",
        "fractional": "19/2",
        "american": "850",
        "winning": false,
        "stopped": false,
        "total": null,
        "handicap": "-1.5",
        "participants": "18731",
        "created_at": "2022-03-24T07:31:45.000000Z",
        "original_label": null,
        "latest_bookmaker_update": "2022-03-29 19:28:28"
      },
      {
        "id": 484267811,
        "fixture_id": 18475817,
        "market_id": 80,
        "bookmaker_id": 35,
        "label": "Under",
        "value": "2.34",
        "name": "1.25",
        "sort_order": null,
        "market_description": "Goals Over/Under",
        "probability": "42.74%",
        "dp3": "2.340",
        "fractional": "89/38",
        "american": "134",
        "winning": true,
        "stopped": false,
        "total": "1.25",
        "handicap": null,
        "participants": null,
        "created_at": "2022-03-24T06:05:19.000000Z",
        "original_label": null,
        "latest_bookmaker_update": "2022-03-29 19:28:28"
      },
      {
        "id": 484267814,
        "fixture_id": 18475817,
        "market_id": 80,
        "bookmaker_id": 35,
        "label": "Over",
        "value": "1.63",
        "name": "1.25",
        "sort_order": null,
        "market_description": "Goals Over/Under",
        "probability": "61.35%",
        "dp3": "1.630",
        "fractional": "31/19",
        "american": "-159",
        "winning": false,
        "stopped": false,
        "total": "1.25",
        "handicap": null,
        "participants": null,
        "created_at": "2022-03-24T06:05:19.000000Z",
        "original_label": null,
        "latest_bookmaker_update": "2022-03-29 19:28:28"
      },
      {
        "id": 484267818,
        "fixture_id": 18475817,
        "market_id": 80,
        "bookmaker_id": 35,
        "label": "Over",
        "value": "2.08",
        "name": "1.5",
        "sort_order": null,
        "market_description": "Goals Over/Under",
        "probability": "48.08%",
        "dp3": "2.080",
        "fractional": "52/25",
        "american": "108",
        "winning": false,
        "stopped": false,
        "total": "1.5",
        "handicap": null,
        "participants": null,
        "created_at": "2022-03-24T06:05:19.000000Z",
        "original_label": null,
        "latest_bookmaker_update": "2022-03-29 19:28:28"
      },
      {
        "id": 484267820,
        "fixture_id": 18475817,
        "market_id": 80,
        "bookmaker_id": 35,
        "label": "Under",
        "value": "1.83",
        "name": "1.5",
        "sort_order": null,
        "market_description": "Goals Over/Under",
        "probability": "54.64%",
        "dp3": "1.830",
        "fractional": "64/35",
        "american": "-121",
        "winning": true,
        "stopped": false,
        "total": "1.5",
        "handicap": null,
        "participants": null,
        "created_at": "2022-03-24T06:05:19.000000Z",
        "original_label": null,
        "latest_bookmaker_update": "2022-03-29 19:28:28"
      }
    ]
  },
  "subscription": [
    {
      "meta": {
        "current_timestamp": 1782409709,
        "next_billing_cycle": "2026-07-09T13:20:20 UTC"
      },
      "plans": [
        {
          "plan": "Pro - Trialing until 2026-07-09 13:20:20",
          "sport": "Football",
          "category": "Advanced"
        },
        {
          "plan": "Euro Club Tournaments",
          "sport": "Football",
          "category": "All-in"
        },
        {
          "plan": "International Tournaments",
          "sport": "Football",
          "category": "All-in"
        }
      ],
      "add_ons": [
        {
          "add_on": "50000 API Calls - Trialing until 2026-07-09 13:20:20",
          "sport": "Football",
          "category": "Calls"
        },
        {
          "add_on": "130 Extra Leagues - Trialing until 2026-07-09 13:20:20",
          "sport": "Football",
          "category": "Extra leagues"
        },
        {
          "add_on": "Transfer Rumours - Trialing until 2026-07-09 13:20:20",
          "sport": "Football",
          "category": "Transfer rumours"
        },
        {
          "add_on": "Expected Lineups - Trialing until 2026-07-09 13:20:20",
          "sport": "Football",
          "category": "Lineups"
        },
        {
          "add_on": "News - Trialing until 2026-07-09 13:20:20",
          "sport": "Football",
          "category": "News"
        },
        {
          "add_on": "Match Facts - Trialing until 2026-07-09 13:20:20",
          "sport": "Football",
          "category": "Match facts"
        }
      ],
      "widgets": [],
      "bundles": [
        {
          "bundle": "Odds & Predictions - Trialing until 2026-07-09 13:20:20",
          "sport": "Football",
          "category": "Odds - Predictions"
        },
        {
          "bundle": "Pressure Index & xG - Trialing until 2026-07-09 13:20:20",
          "sport": "Football",
          "category": "Pressure - Expected"
        }
      ]
    }
  ],
  "rate_limit": {
    "resets_in_seconds": 3481,
    "remaining": 52993,
    "requested_entity": "Fixture"
  },
  "timezone": "UTC"
}